CHAID/__init__.py
CHAID/__main__.py
CHAID/column.py
CHAID/graph.py
CHAID/invalid_split_reason.py
CHAID/mapping_dict.py
CHAID/node.py
CHAID/split.py
CHAID/stats.py
CHAID/tree.py
CHAID-5.4.2.dist-info/LICENSE.txt
CHAID-5.4.2.dist-info/METADATA
CHAID-5.4.2.dist-info/WHEEL
CHAID-5.4.2.dist-info/top_level.txt
CHAID-5.4.2.dist-info/RECORD
